qpu/__init__.py
qpu/dwave/__init__.py
qpu/dwave/cryptography/__init__.py
qpu/dwave/cryptography/trng.py
qpu/ibm/__init__.py
qpu/ibm/cryptography/__init__.py
qpu/ibm/cryptography/trng.py
qpu-0.0.4.dist-info/AUTHORS.rst
qpu-0.0.4.dist-info/LICENSE.txt
qpu-0.0.4.dist-info/METADATA
qpu-0.0.4.dist-info/WHEEL
qpu-0.0.4.dist-info/top_level.txt
qpu-0.0.4.dist-info/RECORD
